pixqrcodegen/__init__.py
pixqrcodegen/pixqrcodegen.py
pixqrcodegen-0.6.dist-info/LICENSE.txt
pixqrcodegen-0.6.dist-info/METADATA
pixqrcodegen-0.6.dist-info/WHEEL
pixqrcodegen-0.6.dist-info/top_level.txt
pixqrcodegen-0.6.dist-info/RECORD
