Metadata-Version: 2.1
Name: pixqrcodegen
Version: 0.6
Summary: Gera a Payload do PIX e o QR Code
Home-page: https://github.com/Alexsussa/pixqrcodegen
Author: Alex Pinheiro
License: MIT
Keywords: qrcode,payload,qrcode-generator,pix,pix-payload-generator
Classifier: Development Status :: 5 - Production/Stable
Classifier: Intended Audience :: Developers
Classifier: License :: OSI Approved :: MIT License
Classifier: Natural Language :: Portuguese (Brazilian)
Classifier: Operating System :: OS Independent
Requires-Python: >= 3.6
License-File: LICENSE.txt
Requires-Dist: crcmod
Requires-Dist: qrcode
Requires-Dist: pillow
